immutables/__init__.py
immutables/_map.cp38-win_amd64.pyd
immutables/_map.pyi
immutables/_protocols.py
immutables/_testutils.py
immutables/_version.py
immutables/map.py
immutables/py.typed
immutables-0.21.dist-info/LICENSE
immutables-0.21.dist-info/LICENSE-APACHE
immutables-0.21.dist-info/METADATA
immutables-0.21.dist-info/NOTICE
immutables-0.21.dist-info/WHEEL
immutables-0.21.dist-info/top_level.txt
immutables-0.21.dist-info/RECORD
