Metadata-Version: 2.1
Name: immutables
Version: 0.21
Summary: Immutable Collections
Author-email: MagicStack Inc <hello@magic.io>
License: Apache License, Version 2.0
Project-URL: github, https://github.com/MagicStack/immutables
Keywords: collections,immutable,hamt
Classifier: License :: OSI Approved :: Apache Software License
Classifier: Intended Audience :: Developers
Classifier: Programming Language :: Python :: 3 :: Only
Classifier: Programming Language :: Python :: 3.8
Classifier: Programming Language :: Python :: 3.9
Classifier: Programming Language :: Python :: 3.10
Classifier: Programming Language :: Python :: 3.11
Classifier: Programming Language :: Python :: 3.12
Classifier: Programming Language :: Python :: Implementation :: CPython
Classifier: Operating System :: POSIX
Classifier: Operating System :: MacOS :: MacOS X
Classifier: Operating System :: Microsoft :: Windows
Classifier: Topic :: Software Development :: Libraries
Requires-Python: >=3.8.0
License-File: LICENSE
License-File: LICENSE-APACHE
License-File: NOTICE
Provides-Extra: test
Requires-Dist: flake8~=5.0; extra == "test"
Requires-Dist: pycodestyle~=2.9; extra == "test"
Requires-Dist: mypy~=1.4; extra == "test"
Requires-Dist: pytest~=7.4; extra == "test"
